Metadata-Version: 2.1
Name: vkplaylive
Version: 0.2
Summary: module for connecting to vkplay live and working with it
Author-email: michailcoding32@gmail.com
